<?xml version="1.0" ?>
<container xmlns="http://symfony.com/schema/dic/services"
    xmlns:xsi="http://www.w3.org/2001/XMLSchema-instance"
    xsi:schemaLocation="http://symfony.com/schema/dic/services http://symfony.com/schema/dic/services/services-1.0.xsd">
    <services>
        <service id="krak.symfony_playground.playground_command" class="Krak\SymfonyPlayground\Command\PlaygroundCommand" public="false">
            <argument></argument>
            <argument>%kernel.project_dir%</argument>
            <tag name="console.command" command="playground"/>
        </service>
    </services>
</container>
